devintest/__init__.py
devintest/client.py
devintest/core/__init__.py
devintest/core/api_error.py
devintest/core/client_wrapper.py
devintest/core/datetime_utils.py
devintest/core/file.py
devintest/core/force_multipart.py
devintest/core/http_client.py
devintest/core/http_response.py
devintest/core/jsonable_encoder.py
devintest/core/pydantic_utilities.py
devintest/core/query_encoder.py
devintest/core/remove_none_from_dict.py
devintest/core/request_options.py
devintest/core/serialization.py
devintest/imdb/__init__.py
devintest/imdb/client.py
devintest/imdb/errors/__init__.py
devintest/imdb/errors/movie_does_not_exist_error.py
devintest/imdb/raw_client.py
devintest/imdb/types/__init__.py
devintest/imdb/types/create_movie_request.py
devintest/imdb/types/movie.py
devintest/imdb/types/movie_id.py
devintest/py.typed
devintest/version.py
devin_new_test_package-0.1.3.dist-info/METADATA
devin_new_test_package-0.1.3.dist-info/WHEEL
devin_new_test_package-0.1.3.dist-info/RECORD
